moviq_qgis/__init__.py
moviq_qgis/__main__.py
moviq_qgis/qgis_annimated.py
moviq_qgis/qgis_export.py
moviq_qgis-0.1.0.dist-info/METADATA
moviq_qgis-0.1.0.dist-info/WHEEL
moviq_qgis-0.1.0.dist-info/entry_points.txt
moviq_qgis-0.1.0.dist-info/RECORD
