Metadata-Version: 2.1
Name: moviq-qgis
Version: 0.1.0
Summary: Creates an annimated gif from GeoTiff images
License: Proprietary
Author: h3dema
Author-email: henrique.duartemoura@imec.be
Requires-Python: >=3.10,<4.0
Classifier: License :: Other/Proprietary License
Classifier: Programming Language :: Python :: 3
Classifier: Programming Language :: Python :: 3.10
Classifier: Programming Language :: Python :: 3.11
Classifier: Programming Language :: Python :: 3.12
Requires-Dist: click (>=8.1,<9.0)
Requires-Dist: pillow (>=10.3,<11.0)
